odoo/addons/sale_financial_risk_info/README.rst
odoo/addons/sale_financial_risk_info/__init__.py
odoo/addons/sale_financial_risk_info/__manifest__.py
odoo/addons/sale_financial_risk_info/i18n/es.po
odoo/addons/sale_financial_risk_info/i18n/sale_financial_risk_info.pot
odoo/addons/sale_financial_risk_info/models/__init__.py
odoo/addons/sale_financial_risk_info/models/res_partner.py
odoo/addons/sale_financial_risk_info/models/sale.py
odoo/addons/sale_financial_risk_info/readme/CONFIGURE.rst
odoo/addons/sale_financial_risk_info/readme/CONTRIBUTORS.rst
odoo/addons/sale_financial_risk_info/readme/DESCRIPTION.rst
odoo/addons/sale_financial_risk_info/readme/USAGE.rst
odoo/addons/sale_financial_risk_info/static/description/icon.png
odoo/addons/sale_financial_risk_info/static/description/index.html
odoo/addons/sale_financial_risk_info/tests/__init__.py
odoo/addons/sale_financial_risk_info/tests/test_sale_financial_risk_info.py
odoo/addons/sale_financial_risk_info/views/res_partner_view.xml
odoo/addons/sale_financial_risk_info/views/sale_order_view.xml
odoo13_addon_sale_financial_risk_info-13.0.1.0.1.dev5.dist-info/METADATA
odoo13_addon_sale_financial_risk_info-13.0.1.0.1.dev5.dist-info/WHEEL
odoo13_addon_sale_financial_risk_info-13.0.1.0.1.dev5.dist-info/top_level.txt
odoo13_addon_sale_financial_risk_info-13.0.1.0.1.dev5.dist-info/RECORD
